symbolipy/__init__.py
symbolipy/symbol_interface.py
symbolipy-1.0.0.dist-info/LICENSE
symbolipy-1.0.0.dist-info/METADATA
symbolipy-1.0.0.dist-info/WHEEL
symbolipy-1.0.0.dist-info/top_level.txt
symbolipy-1.0.0.dist-info/RECORD
