Metadata-Version: 2.1
Name: symbolipy
Version: 1.0.0
Summary: Present mathematical equality and inequality in symbol format.
Author-email: Pouya Motakef <p.motakef@gmail.com>
Maintainer-email: Pouya Motakef <p.motakef@gmail.com>
License: BSD 2-Clause License
Project-URL: Homepage, https://github.com/pmotakef/symbolipy
Project-URL: Documentation, https://github.com/pmotakef/symbolipy
Project-URL: Repository, https://github.com/pmotakef/symbolipy
Project-URL: Issues, https://github.com/pmotakef/symbolipy/issues
Project-URL: Changelog, https://github.com/pmotakef/symbolipy/blob/main/CHANGELOG.md
Keywords: symbol
Requires-Python: >=3.8
License-File: LICENSE
Provides-Extra: test
Requires-Dist: pytest ; extra == 'test'
